example/__init__.py
example/run.py
example/worker.py
example/benchmark/__init__.py
example/benchmark/benchmarks.py
example/collection/__init__.py
example/collection/collections.py
example/index/__init__.py
example/index/anserini.py
example/searcher/__init__.py
example/searcher/bm25.py
example/task/__init__.py
example/task/base.py
example/task/rank.py
profane/__init__.py
profane/base.py
profane/cli.py
profane/config_option.py
profane/constants.py
profane/exceptions.py
profane/frozendict.py
profane/sql.py
profane-0.2.4.dist-info/DESCRIPTION.rst
profane-0.2.4.dist-info/METADATA
profane-0.2.4.dist-info/RECORD
profane-0.2.4.dist-info/WHEEL
profane-0.2.4.dist-info/metadata.json
profane-0.2.4.dist-info/top_level.txt
