Metadata-Version: 2.0
Name: profane
Version: 0.2.4
Summary: A library for creating complex experimental pipelines
Home-page: https://github.com/andrewyates/profane
Author: Andrew Yates
Author-email: UNKNOWN
License: UNKNOWN
Platform: UNKNOWN
Classifier: Programming Language :: Python :: 3
Classifier: Operating System :: OS Independent
Requires-Python: >=3.6
Requires-Dist: PyYAML (>=5)
Requires-Dist: colorama
Requires-Dist: docopt
Requires-Dist: numpy (>=1.17)
Requires-Dist: sqlalchemy
Requires-Dist: sqlalchemy-utils
